experiment_design/__init__.py
experiment_design/experiment_designer.py
experiment_design/optimize.py
experiment_design/orthogonal_sampling.py
experiment_design/random_sampling.py
experiment_design/scorers.py
experiment_design/variable/__init__.py
experiment_design/variable/space.py
experiment_design/variable/variable.py
experimental_design-0.0.0.dist-info/LICENSE
experimental_design-0.0.0.dist-info/METADATA
experimental_design-0.0.0.dist-info/WHEEL
experimental_design-0.0.0.dist-info/RECORD
